piboufilings/__init__.py
piboufilings/config/__init__.py
piboufilings/config/settings.py
piboufilings/core/__init__.py
piboufilings/core/downloader.py
piboufilings/core/logger.py
piboufilings/core/rate_limiter.py
piboufilings/parsers/__init__.py
piboufilings/parsers/form_13f_parser.py
piboufilings/parsers/form_nport_parser.py
piboufilings/parsers/form_sec16_parser.py
piboufilings/parsers/parser_utils.py
piboufilings-0.4.0.dist-info/licenses/LICENCE
piboufilings-0.4.0.dist-info/METADATA
piboufilings-0.4.0.dist-info/WHEEL
piboufilings-0.4.0.dist-info/top_level.txt
piboufilings-0.4.0.dist-info/RECORD
