Metadata-Version: 2.4
Name: piboufilings
Version: 0.4.0
Summary: A Python library for downloading and parsing SEC EDGAR filings
Home-page: https://github.com/pibou/piboufilings
Author: Pierre Bouquet
Author-email: pierrebouquet73000@gmail.com
License: Non-Commercial
Project-URL: Bug Reports, https://github.com/pibou/piboufilings/issues
Project-URL: Source, https://github.com/pibou/piboufilings
Keywords: sec,edgar,filings,financial,13f,parser
Classifier: Development Status :: 3 - Alpha
Classifier: Intended Audience :: Financial and Insurance Industry
Classifier: License :: Other/Proprietary License
Classifier: Programming Language :: Python :: 3
Classifier: Programming Language :: Python :: 3.8
Classifier: Programming Language :: Python :: 3.9
Classifier: Programming Language :: Python :: 3.10
Classifier: Programming Language :: Python :: 3.11
Classifier: Topic :: Office/Business :: Financial :: Investment
Requires-Python: >=3.8
License-File: LICENCE
Requires-Dist: pandas>=1.3.0
Requires-Dist: requests>=2.26.0
Requires-Dist: tqdm>=4.62.0
Requires-Dist: urllib3>=1.26.0
Requires-Dist: lxml>=4.9.0
Requires-Dist: python-dateutil>=2.8.2
Provides-Extra: test
Requires-Dist: pytest; extra == "test"
Dynamic: author
Dynamic: author-email
Dynamic: classifier
Dynamic: description
Dynamic: description-content-type
Dynamic: home-page
Dynamic: keywords
Dynamic: license
Dynamic: license-file
Dynamic: project-url
Dynamic: provides-extra
Dynamic: requires-dist
Dynamic: requires-python
Dynamic: summary
